tsukuru/__init__.py
tsukuru-0.0.1.dist-info/WHEEL
tsukuru-0.0.1.dist-info/METADATA
tsukuru-0.0.1.dist-info/RECORD
