Metadata-Version: 2.1
Name: tsukuru
Version: 0.0.1
Summary: GUI Makefile creater
Home-page: https://github.com/senrust/tsukuru
License: MIT
Keywords: C,Makefile,GUI
Author: Yohei Osawa
Author-email: yohei.osawa.318.niko8@gmail.com
Requires-Python: >=3.7,<4.0
Classifier: License :: OSI Approved :: MIT License
Classifier: Programming Language :: Python :: 3
Classifier: Programming Language :: Python :: 3.10
Classifier: Programming Language :: Python :: 3.7
Classifier: Programming Language :: Python :: 3.8
Classifier: Programming Language :: Python :: 3.9
Project-URL: Repository, https://github.com/senrust/tsukuru
